redpil/__init__.py
redpil/_static_version.py
redpil/_version.py
redpil/bmp.py
redpil/redpil.py
redpil-0.2.1.dist-info/AUTHORS.md
redpil-0.2.1.dist-info/LICENSE
redpil-0.2.1.dist-info/METADATA
redpil-0.2.1.dist-info/WHEEL
redpil-0.2.1.dist-info/top_level.txt
redpil-0.2.1.dist-info/RECORD
