Metadata-Version: 2.1
Name: redpil
Version: 0.2.1
Summary: Join the wonderland of python, and decode all your images in a numpy compatible way
Home-page: https://github.com/hmaarrfk/redpil
Author: Mark Harfouche
Author-email: mark.harfouche@gmail.com
License: MIT license
Keywords: redpil
Classifier: Development Status :: 2 - Pre-Alpha
Classifier: Intended Audience :: Developers
Classifier: License :: OSI Approved :: MIT License
Classifier: Natural Language :: English
Classifier: Programming Language :: Python :: 3
Classifier: Programming Language :: Python :: 3.10
Classifier: Programming Language :: Python :: 3.11
Classifier: Programming Language :: Python :: 3.12
Classifier: Programming Language :: Python :: 3.13
Requires-Python: >=3.10
License-File: LICENSE
License-File: AUTHORS.md
Requires-Dist: numpy
